bettersleepy/__init__.py
BetterSleePy-0.1.3.dist-info/METADATA
BetterSleePy-0.1.3.dist-info/WHEEL
BetterSleePy-0.1.3.dist-info/top_level.txt
BetterSleePy-0.1.3.dist-info/RECORD
