Metadata-Version: 2.1
Name: BetterSleePy
Version: 0.1.3
Summary: Makes the Python sleep module easier a bit.
Home-page: https://github.com/octopus1348/bettersleepy
Author: Czira Zsombor
Author-email: czirazsombor313@icloud.com
